topocor/__init__.py
topocor/_modidx.py
topocor/core.py
topocor-0.0.1.dist-info/LICENSE
topocor-0.0.1.dist-info/METADATA
topocor-0.0.1.dist-info/WHEEL
topocor-0.0.1.dist-info/entry_points.txt
topocor-0.0.1.dist-info/top_level.txt
topocor-0.0.1.dist-info/RECORD
